openqlab/__init__.py
openqlab/_typing.py
openqlab/analysis/__init__.py
openqlab/analysis/cavity.py
openqlab/analysis/control.py
openqlab/analysis/electromagnetic_wave.py
openqlab/analysis/gaussian_beam.py
openqlab/analysis/phase.py
openqlab/analysis/servo_design.py
openqlab/analysis/squeezing.py
openqlab/conversion/__init__.py
openqlab/conversion/db.py
openqlab/conversion/utils.py
openqlab/conversion/wavelength.py
openqlab/io/__init__.py
openqlab/io/base_importer.py
openqlab/io/data_container.py
openqlab/io/importers/__init__.py
openqlab/io/importers/_old_importers/__init__.py
openqlab/io/importers/_old_importers/entanglement_hdf5.py
openqlab/io/importers/_old_importers/labview.py
openqlab/io/importers/ascii.py
openqlab/io/importers/ascii_header.py
openqlab/io/importers/data_container_csv.py
openqlab/io/importers/gwinstek.py
openqlab/io/importers/gwinstek_lsf.py
openqlab/io/importers/hp4395a.py
openqlab/io/importers/hp4395a_gpib.py
openqlab/io/importers/keysight_binary.py
openqlab/io/importers/keysight_csv.py
openqlab/io/importers/keysight_fra.py
openqlab/io/importers/keysight_visa.py
openqlab/io/importers/rohde_schwarz.py
openqlab/io/importers/rohde_schwarz_osci_visa.py
openqlab/io/importers/rohde_schwarz_visa.py
openqlab/io/importers/tektronix.py
openqlab/io/importers/tektronix_dpx.py
openqlab/io/importers/tektronix_spectrogram.py
openqlab/io/importers/utils.py
openqlab/plots/__init__.py
openqlab/plots/frequency_domain.py
openqlab/plots/gaussian_beam.py
openqlab/plots/time_domain.py
openqlab/spacing.py
openqlab-0.4.4.dist-info/METADATA
openqlab-0.4.4.dist-info/WHEEL
openqlab-0.4.4.dist-info/licenses/LICENSE
openqlab-0.4.4.dist-info/RECORD
