Metadata-Version: 2.4
Name: openqlab
Version: 0.4.4
Summary: An open-source collection of tools for quantum-optics experiments
License-File: LICENSE
Author: Jan Petermann
Author-email: jpeterma@physnet.uni-hamburg.de
Maintainer: Christian Darsow-Fromm
Maintainer-email: cdarsowf@physnet.uni-hamburg.de
Requires-Python: >=3.10.1,<3.16
Classifier: Programming Language :: Python :: 3
Classifier: Programming Language :: Python :: 3.11
Classifier: Programming Language :: Python :: 3.12
Classifier: Programming Language :: Python :: 3.13
Classifier: Programming Language :: Python :: 3.14
Provides-Extra: hdf
Provides-Extra: visa
Requires-Dist: PyVISA (>=1.11.1,<2.0.0) ; extra == "visa"
Requires-Dist: importlib-metadata (>=8.0,<9.0)
Requires-Dist: matplotlib (>=3.2.1,<4)
Requires-Dist: numpy (>=1.18,<3.0)
Requires-Dist: pandas (>=1.4,<3.0)
Requires-Dist: pyserial (>=3.5,<4.0)
Requires-Dist: pyvisa-py (>=0.6.0,<1) ; extra == "visa"
Requires-Dist: scipy (>=1.9.3,<2.0)
Requires-Dist: tables (>=3.6.1,<4) ; extra == "hdf"
Requires-Dist: wcwidth (>=0.2.5,<0.3.0)
Project-URL: Documentation, https://las-nq-serv.physnet.uni-hamburg.de/python/openqlab/
Project-URL: Repository, https://gitlab.com/las-nq/openqlab
